blip/__init__.py
blip/configs/bert_config.json
blip/configs/caption_coco.yaml
blip/configs/med_config.json
blip/configs/nlvr.yaml
blip/configs/nocaps.yaml
blip/configs/pretrain.yaml
blip/configs/retrieval_coco.yaml
blip/configs/retrieval_flickr.yaml
blip/configs/retrieval_msrvtt.yaml
blip/configs/vqa.yaml
blip/data/__init__.py
blip/data/coco_karpathy_dataset.py
blip/data/flickr30k_dataset.py
blip/data/nlvr_dataset.py
blip/data/nocaps_dataset.py
blip/data/pretrain_dataset.py
blip/data/utils.py
blip/data/video_dataset.py
blip/data/vqa_dataset.py
blip/models/__init__.py
blip/models/blip.py
blip/models/blip_itm.py
blip/models/blip_nlvr.py
blip/models/blip_pretrain.py
blip/models/blip_retrieval.py
blip/models/blip_vqa.py
blip/models/med.py
blip/models/nlvr_encoder.py
blip/models/vit.py
blip_ci-0.0.5.dist-info/LICENSE.txt
blip_ci-0.0.5.dist-info/METADATA
blip_ci-0.0.5.dist-info/WHEEL
blip_ci-0.0.5.dist-info/top_level.txt
blip_ci-0.0.5.dist-info/RECORD
