Metadata-Version: 2.1
Name: blip-ci
Version: 0.0.5
Summary: BLIP library for use with CLIP Interrogator
Home-page: https://github.com/pharmapsychotic/BLIP
Author: salesforce
Author-email: 
License: BSD-3
Classifier: Programming Language :: Python :: 3
Classifier: License :: OSI Approved :: MIT License
Classifier: Operating System :: OS Independent
Classifier: Development Status :: 2 - Pre-Alpha
Requires-Python: >=3.6
License-File: LICENSE.txt
Requires-Dist: timm (==0.4.12)
Requires-Dist: transformers (>=4.15.0)
Requires-Dist: fairscale (==0.4.4)
Provides-Extra: all
Requires-Dist: pytest ; extra == 'all'
Provides-Extra: dev
Requires-Dist: pytest ; extra == 'dev'
